README.md
setup.cfg
setup.py
file_iterator/Exceptions.py
file_iterator/FileGroupIterator.py
file_iterator/FileIterator.py
file_iterator/Utils.py
file_iterator/__init__.py
file_iterator.egg-info/PKG-INFO
file_iterator.egg-info/SOURCES.txt
file_iterator.egg-info/dependency_links.txt
file_iterator.egg-info/not-zip-safe
file_iterator.egg-info/requires.txt
file_iterator.egg-info/top_level.txt
tests/Exceptions_test.py
tests/FileGroupIterator_test.py
tests/FileIterator_test.py
tests/Utils_test.py
tests/__init__.py
tests/fileiteratortst.py