Metadata-Version: 2.1
Name: file-iterator
Version: 1.0.1
Summary: Utilities for iterating file contents.
Home-page: https://github.com/ferancona/file-iterator
Author: Fernando Ancona
Author-email: f.anconac@gmail.com
License: MIT
Download-URL: https://github.com/ferancona/file-iterator/archive/1.0.1.tar.gz
Keywords: FILE,READ,CONTENT,ITERATION
Platform: UNKNOWN
Classifier: Development Status :: 4 - Beta
Classifier: Intended Audience :: Developers
Classifier: License :: OSI Approved :: MIT License
Classifier: Operating System :: OS Independent
Classifier: Programming Language :: Python :: 3
Classifier: Programming Language :: Python :: 3.5
Classifier: Programming Language :: Python :: 3.6
Classifier: Programming Language :: Python :: 3.7
Classifier: Programming Language :: Python :: 3.8
Classifier: Topic :: Software Development
Requires-Python: >=3.5
